some_models/__init__.py
some_models/constants.py
some_models/exceptions.py
some_models/fastapi_dependencies.py
some_models/models/__init__.py
some_models/models/base.py
some_models/models/product.py
some_models/models/purchase.py
some_models/models/shop.py
some_models/models/user.py
some_models-0.4.1.dist-info/WHEEL
some_models-0.4.1.dist-info/METADATA
some_models-0.4.1.dist-info/RECORD
