Metadata-Version: 2.1
Name: some-models
Version: 0.4.1
Summary: Учебная библиотека. Тут находятся orm модели нужные в нескольких микросервисах, что бы не нарушать DRY.
Author: koevgeny10
Author-email: koevgeny10@gmail.com
Requires-Python: >=3.10,<4.0
Classifier: Programming Language :: Python :: 3
Classifier: Programming Language :: Python :: 3.10
Requires-Dist: SQLAlchemy[postgresql] (>=1.4.33,<2.0.0)
Requires-Dist: passlib[bcrypt] (>=1.7.4,<2.0.0)
Requires-Dist: sqlalchemy-utils (>=0.38.2,<0.39.0)
